dovecot_userpassdb.py
dovecot_userpassdb-0.1.1.dist-info/LICENSE
dovecot_userpassdb-0.1.1.dist-info/METADATA
dovecot_userpassdb-0.1.1.dist-info/WHEEL
dovecot_userpassdb-0.1.1.dist-info/entry_points.txt
dovecot_userpassdb-0.1.1.dist-info/top_level.txt
dovecot_userpassdb-0.1.1.dist-info/RECORD
