Metadata-Version: 2.1
Name: dovecot-userpassdb
Version: 0.1.1
Summary: Dovecot user-controllable passwords
Home-page: https://github.com/koniiiik/dovecot-userpassdb
Author: Michal Petrucha
Author-email: michal.petrucha@koniiiik.org
License: BSD
Keywords: dovecot imap password checkpassword
Classifier: Development Status :: 4 - Beta
Classifier: Intended Audience :: System Administrators
Classifier: Topic :: Communications :: Email :: Post-Office :: IMAP
Classifier: Topic :: Communications :: Email :: Post-Office :: POP3
Classifier: Topic :: System :: Systems Administration :: Authentication/Directory
Classifier: License :: OSI Approved :: BSD License
Classifier: Programming Language :: Python :: 3
Classifier: Operating System :: POSIX
License-File: LICENSE
Requires-Dist: passlib
Provides-Extra: test
Requires-Dist: pytest ; extra == 'test'
